fledge_cli/__about__.py
fledge_cli/__init__.py
fledge_cli/__main__.py
fledge_cli/data/gitignore
fledge_cli/data/gitlint
fledge_cli/data/mkdocs.yml
fledge_cli/data/pre-commit-config.yaml
fledge_cli/data/pyproject-update.toml
fledge_cli/data/yamllint
fledge_cli/data/github/copilot-instructions.md
fledge_cli/data/github/workflows/publish-docs.yml
fledge_cli/data/github/workflows/release.yml
fledge_cli-0.0.1.post1.dist-info/METADATA
fledge_cli-0.0.1.post1.dist-info/WHEEL
fledge_cli-0.0.1.post1.dist-info/entry_points.txt
fledge_cli-0.0.1.post1.dist-info/licenses/LICENSE.txt
fledge_cli-0.0.1.post1.dist-info/RECORD
