Metadata-Version: 2.4
Name: fledge-cli
Version: 0.0.1.post1
Summary: Bootstrap Python projects with best-practice development configurations
Project-URL: Documentation, https://bytehexe.github.io/fledge-cli/
Project-URL: Source, https://github.com/bytehexe/fledge-cli
Author: Janna Hopp
License-Expression: MIT
License-File: LICENSE.txt
Classifier: Development Status :: 4 - Beta
Classifier: Programming Language :: Python
Classifier: Programming Language :: Python :: 3.8
Classifier: Programming Language :: Python :: 3.9
Classifier: Programming Language :: Python :: 3.10
Classifier: Programming Language :: Python :: 3.11
Classifier: Programming Language :: Python :: 3.12
Classifier: Programming Language :: Python :: Implementation :: CPython
Classifier: Programming Language :: Python :: Implementation :: PyPy
Requires-Python: >=3.8
Requires-Dist: click
Requires-Dist: platformdirs
Requires-Dist: pythonsed
Requires-Dist: toml
Requires-Dist: tomlkit
